{
  "grid_id": 63,
  "total_listings": 5,
  "discovery_timestamp": "2025-12-28 06:58:07",
  "listings": {
    "18274185": {
      "room_id": 18274185,
      "latitude": 38.31947,
      "longitude": -122.27103,
      "grid_id_assigned": null,
      "grid_id_source": 63.0,
      "bbox_id": "38.314340_-122.276690_38.322090_-122.266180",
      "pass_id": 0,
      "discovered_at": "2025-12-28 06:55:13",
      "raw_data": {
        "room_id": 18274185,
        "category": "",
        "structuredContent": {
          "__typename": "ExploreStructuredContent",
          "distance": [],
          "mapCategoryInfo": [],
          "mapPrimaryLine": [],
          "mapSecondaryLine": [
            {
              "__typename": "MainSectionMessage",
              "body": "Jan 1 – 6",
              "bodyA11yLabel": null,
              "bodyType": null,
              "fontWeight": null,
              "headline": null,
              "type": "DATE"
            }
          ],
          "primaryLine": [
            {
              "__typename": "MainSectionMessage",
              "body": "1 bedroom",
              "bodyA11yLabel": null,
              "bodyType": null,
              "fontWeight": null,
              "headline": null,
              "type": "BEDINFO"
            },
            {
              "__typename": "MainSectionMessage",
              "body": "3 beds",
              "bodyA11yLabel": null,
              "bodyType": null,
              "fontWeight": null,
              "headline": null,
              "type": "BEDINFO"
            }
          ],
          "secondaryLine": [
            {
              "__typename": "MainSectionMessage",
              "body": "Jan 1 – 6",
              "bodyA11yLabel": null,
              "bodyType": null,
              "fontWeight": null,
              "headline": null,
              "type": "DATE"
            }
          ],
          "reviewSnippet": null,
          "explanation": []
        },
        "passportData": {},
        "paymentMessages": [],
        "kind": "",
        "name": "BJ's Nest Vacation Rental (VR09-0038)",
        "title": "Apartment in Napa",
        "type": "",
        "long_stay_discount": {},
        "fee": {
          "airbnb": {},
          "cleaning": {}
        },
        "price": {
          "unit": {
            "qualifier": "for 5 nights",
            "curency_symbol": "$",
            "amount": 1690.0,
            "discount": 1449.0
          },
          "total": {
            "currency_symbol": "",
            "amount": 0
          },
          "break_down": [
            {
              "description": "5 nights x $289.69",
              "amount": 1448.0,
              "currency": "$.44"
            }
          ]
        },
        "rating": {
          "value": 4.76,
          "reviewCount": "42"
        },
        "images": [
          {
            "url": "https://a0.muscache.com/im/pictures/f795b806-4666-4e79-9bb6-3e1e2db18712.jpg"
          },
          {
            "url": "https://a0.muscache.com/im/pictures/cf692d95-6e10-4819-abe3-029d867c8ae1.jpg"
          },
          {
            "url": "https://a0.muscache.com/im/pictures/d975b41e-86cc-41c0-b2df-d5de33b13769.jpg"
          },
          {
            "url": "https://a0.muscache.com/im/pictures/c51d8d42-0085-4169-a716-7175573393f2.jpg"
          },
          {
            "url": "https://a0.muscache.com/im/pictures/66e9a335-ec31-4a23-8d87-7b80079e4b46.jpg"
          },
          {
            "url": "https://a0.muscache.com/im/pictures/68d7cc7b-ac8f-433c-8f9d-c9afd0391353.jpg"
          }
        ],
        "badges": [],
        "coordinates": {
          "latitude": 38.31947,
          "longitud": -122.27103
        }
      }
    },
    "1172468437139886591": {
      "room_id": 1172468437139886591,
      "latitude": 38.3151,
      "longitude": -122.2763,
      "grid_id_assigned": null,
      "grid_id_source": 63.0,
      "bbox_id": "38.314340_-122.276690_38.322090_-122.266180",
      "pass_id": 0,
      "discovered_at": "2025-12-28 06:55:13",
      "raw_data": {
        "room_id": 1172468437139886591,
        "category": "",
        "structuredContent": {
          "__typename": "ExploreStructuredContent",
          "distance": [],
          "mapCategoryInfo": [],
          "mapPrimaryLine": [],
          "mapSecondaryLine": [
            {
              "__typename": "MainSectionMessage",
              "body": "Jan 4 – 9",
              "bodyA11yLabel": null,
              "bodyType": null,
              "fontWeight": null,
              "headline": null,
              "type": "DATE"
            }
          ],
          "primaryLine": [
            {
              "__typename": "MainSectionMessage",
              "body": "1 bedroom",
              "bodyA11yLabel": null,
              "bodyType": null,
              "fontWeight": null,
              "headline": null,
              "type": "BEDINFO"
            },
            {
              "__typename": "MainSectionMessage",
              "body": "1 king bed",
              "bodyA11yLabel": null,
              "bodyType": null,
              "fontWeight": null,
              "headline": null,
              "type": "BEDINFO"
            }
          ],
          "secondaryLine": [
            {
              "__typename": "MainSectionMessage",
              "body": "Jan 4 – 9",
              "bodyA11yLabel": null,
              "bodyType": null,
              "fontWeight": null,
              "headline": null,
              "type": "DATE"
            }
          ],
          "reviewSnippet": null,
          "explanation": []
        },
        "passportData": {},
        "paymentMessages": [],
        "kind": "",
        "name": "Small sitting area & in-room fireplace",
        "title": "Hotel in Napa",
        "type": "",
        "long_stay_discount": {},
        "fee": {
          "airbnb": {},
          "cleaning": {}
        },
        "price": {
          "unit": {
            "qualifier": "for 5 nights",
            "curency_symbol": "$",
            "amount": 1548.0
          },
          "total": {
            "currency_symbol": "",
            "amount": 0
          },
          "break_down": [
            {
              "description": "5 nights x $309.43",
              "amount": 1547.0,
              "currency": "$.16"
            }
          ]
        },
        "rating": {
          "value": 0,
          "reviewCount": 0
        },
        "images": [
          {
            "url": "https://a0.muscache.com/im/pictures/prohost-api/Hosting-1172468437139886591/original/05d951ed-9085-4e02-9177-74de76936de7.jpeg"
          },
          {
            "url": "https://a0.muscache.com/im/pictures/prohost-api/Hosting-1172468437139886591/original/18cfde8c-b9f4-4f0c-b965-d98384f11572.jpeg"
          },
          {
            "url": "https://a0.muscache.com/im/pictures/prohost-api/Hosting-1172468437139886591/original/f09ef32a-e96c-43cf-9921-0475b78a3a58.jpeg"
          },
          {
            "url": "https://a0.muscache.com/im/pictures/prohost-api/Hosting-1172468437139886591/original/e46837f3-8270-4ed0-892b-89e55ca4c577.jpeg"
          },
          {
            "url": "https://a0.muscache.com/im/pictures/prohost-api/Hosting-1172468437139886591/original/24c48e54-1d0e-41f0-9f9b-66dbc1a91e6c.jpeg"
          },
          {
            "url": "https://a0.muscache.com/im/pictures/prohost-api/Hosting-1172468437139886591/original/8d759b35-f657-49ce-a946-7c8641e7be02.jpeg"
          }
        ],
        "badges": [],
        "coordinates": {
          "latitude": 38.3151,
          "longitud": -122.2763
        }
      }
    },
    "1172469022811377667": {
      "room_id": 1172469022811377667,
      "latitude": 38.3151,
      "longitude": -122.2763,
      "grid_id_assigned": null,
      "grid_id_source": 63.0,
      "bbox_id": "38.314340_-122.276690_38.322090_-122.266180",
      "pass_id": 0,
      "discovered_at": "2025-12-28 06:55:13",
      "raw_data": {
        "room_id": 1172469022811377667,
        "category": "",
        "structuredContent": {
          "__typename": "ExploreStructuredContent",
          "distance": [],
          "mapCategoryInfo": [],
          "mapPrimaryLine": [],
          "mapSecondaryLine": [
            {
              "__typename": "MainSectionMessage",
              "body": "Jan 6 – 11",
              "bodyA11yLabel": null,
              "bodyType": null,
              "fontWeight": null,
              "headline": null,
              "type": "DATE"
            }
          ],
          "primaryLine": [
            {
              "__typename": "MainSectionMessage",
              "body": "1 bedroom",
              "bodyA11yLabel": null,
              "bodyType": null,
              "fontWeight": null,
              "headline": null,
              "type": "BEDINFO"
            },
            {
              "__typename": "MainSectionMessage",
              "body": "1 king bed",
              "bodyA11yLabel": null,
              "bodyType": null,
              "fontWeight": null,
              "headline": null,
              "type": "BEDINFO"
            }
          ],
          "secondaryLine": [
            {
              "__typename": "MainSectionMessage",
              "body": "Jan 6 – 11",
              "bodyA11yLabel": null,
              "bodyType": null,
              "fontWeight": null,
              "headline": null,
              "type": "DATE"
            }
          ],
          "reviewSnippet": null,
          "explanation": []
        },
        "passportData": {},
        "paymentMessages": [],
        "kind": "",
        "name": "River views, private deck & fire pit",
        "title": "Hotel in Napa",
        "type": "",
        "long_stay_discount": {},
        "fee": {
          "airbnb": {},
          "cleaning": {}
        },
        "price": {
          "unit": {
            "qualifier": "for 5 nights",
            "curency_symbol": "$",
            "amount": 2527.0
          },
          "total": {
            "currency_symbol": "",
            "amount": 0
          },
          "break_down": [
            {
              "description": "5 nights x $505.21",
              "amount": 2526.0,
              "currency": "$.05"
            }
          ]
        },
        "rating": {
          "value": 0,
          "reviewCount": 0
        },
        "images": [
          {
            "url": "https://a0.muscache.com/im/pictures/prohost-api/Hosting-1172469022811377667/original/2ebd34bb-3e0b-4504-86fe-dcd69ba33f4c.jpeg"
          },
          {
            "url": "https://a0.muscache.com/im/pictures/prohost-api/Hosting-1172469022811377667/original/e0b2ab60-4015-4281-a537-54334473d8c7.jpeg"
          },
          {
            "url": "https://a0.muscache.com/im/pictures/prohost-api/Hosting-1172469022811377667/original/0d5b78bb-d17c-4244-8dab-6e98b5c2dbbf.jpeg"
          },
          {
            "url": "https://a0.muscache.com/im/pictures/prohost-api/Hosting-1172469022811377667/original/3c54390e-94f2-46e1-b73d-fd5b67a4c96d.jpeg"
          },
          {
            "url": "https://a0.muscache.com/im/pictures/prohost-api/Hosting-1172469022811377667/original/fd37ad50-61f8-4c97-9b0e-a03e5ddf4fd2.jpeg"
          },
          {
            "url": "https://a0.muscache.com/im/pictures/prohost-api/Hosting-1172469022811377667/original/28723557-ff7d-4b32-b66f-ff6d65f509fd.jpeg"
          }
        ],
        "badges": [],
        "coordinates": {
          "latitude": 38.3151,
          "longitud": -122.2763
        }
      }
    },
    "1172468437528826014": {
      "room_id": 1172468437528826014,
      "latitude": 38.3151,
      "longitude": -122.2763,
      "grid_id_assigned": null,
      "grid_id_source": 63.0,
      "bbox_id": "38.314340_-122.276690_38.322090_-122.266180",
      "pass_id": 0,
      "discovered_at": "2025-12-28 06:55:13",
      "raw_data": {
        "room_id": 1172468437528826014,
        "category": "",
        "structuredContent": {
          "__typename": "ExploreStructuredContent",
          "distance": [],
          "mapCategoryInfo": [],
          "mapPrimaryLine": [],
          "mapSecondaryLine": [
            {
              "__typename": "MainSectionMessage",
              "body": "Jan 2 – 7",
              "bodyA11yLabel": null,
              "bodyType": null,
              "fontWeight": null,
              "headline": null,
              "type": "DATE"
            }
          ],
          "primaryLine": [
            {
              "__typename": "MainSectionMessage",
              "body": "1 bedroom",
              "bodyA11yLabel": null,
              "bodyType": null,
              "fontWeight": null,
              "headline": null,
              "type": "BEDINFO"
            },
            {
              "__typename": "MainSectionMessage",
              "body": "1 king bed",
              "bodyA11yLabel": null,
              "bodyType": null,
              "fontWeight": null,
              "headline": null,
              "type": "BEDINFO"
            }
          ],
          "secondaryLine": [
            {
              "__typename": "MainSectionMessage",
              "body": "Jan 2 – 7",
              "bodyA11yLabel": null,
              "bodyType": null,
              "fontWeight": null,
              "headline": null,
              "type": "DATE"
            }
          ],
          "reviewSnippet": null,
          "explanation": []
        },
        "passportData": {},
        "paymentMessages": [],
        "kind": "",
        "name": "Cozy room with fireplace & partial views",
        "title": "Hotel in Napa",
        "type": "",
        "long_stay_discount": {},
        "fee": {
          "airbnb": {},
          "cleaning": {}
        },
        "price": {
          "unit": {
            "qualifier": "for 5 nights",
            "curency_symbol": "$",
            "amount": 1930.0
          },
          "total": {
            "currency_symbol": "",
            "amount": 0
          },
          "break_down": [
            {
              "description": "5 nights x $385.84",
              "amount": 1929.0,
              "currency": "$.18"
            }
          ]
        },
        "rating": {
          "value": 0,
          "reviewCount": 0
        },
        "images": [
          {
            "url": "https://a0.muscache.com/im/pictures/prohost-api/Hosting-1172468437528826014/original/11a25cdb-ff39-4dca-a32a-e6b40a178a03.jpeg"
          },
          {
            "url": "https://a0.muscache.com/im/pictures/prohost-api/Hosting-1172468437528826014/original/105e8135-0569-4fc3-b2e4-dc85f92bf5af.jpeg"
          },
          {
            "url": "https://a0.muscache.com/im/pictures/prohost-api/Hosting-1172468437528826014/original/1503da15-4360-457a-a9d8-54c266629b11.jpeg"
          },
          {
            "url": "https://a0.muscache.com/im/pictures/prohost-api/Hosting-1172468437528826014/original/f62f8e97-8b9c-4fa6-a610-0bd9b8af4737.jpeg"
          },
          {
            "url": "https://a0.muscache.com/im/pictures/prohost-api/Hosting-1172468437528826014/original/00cb5a14-7121-4a85-8e33-b22d2e0051e0.jpeg"
          },
          {
            "url": "https://a0.muscache.com/im/pictures/prohost-api/Hosting-1172468437528826014/original/1ae26060-0f9c-4ab4-ab59-a201dcc83503.jpeg"
          }
        ],
        "badges": [],
        "coordinates": {
          "latitude": 38.3151,
          "longitud": -122.2763
        }
      }
    },
    "1172469018370689733": {
      "room_id": 1172469018370689733,
      "latitude": 38.3151,
      "longitude": -122.2763,
      "grid_id_assigned": null,
      "grid_id_source": 63.0,
      "bbox_id": "38.314340_-122.276690_38.322090_-122.266180",
      "pass_id": 0,
      "discovered_at": "2025-12-28 06:55:13",
      "raw_data": {
        "room_id": 1172469018370689733,
        "category": "",
        "structuredContent": {
          "__typename": "ExploreStructuredContent",
          "distance": [],
          "mapCategoryInfo": [],
          "mapPrimaryLine": [],
          "mapSecondaryLine": [
            {
              "__typename": "MainSectionMessage",
              "body": "Jan 7 – 12",
              "bodyA11yLabel": null,
              "bodyType": null,
              "fontWeight": null,
              "headline": null,
              "type": "DATE"
            }
          ],
          "primaryLine": [
            {
              "__typename": "MainSectionMessage",
              "body": "1 bedroom",
              "bodyA11yLabel": null,
              "bodyType": null,
              "fontWeight": null,
              "headline": null,
              "type": "BEDINFO"
            },
            {
              "__typename": "MainSectionMessage",
              "body": "1 king bed",
              "bodyA11yLabel": null,
              "bodyType": null,
              "fontWeight": null,
              "headline": null,
              "type": "BEDINFO"
            }
          ],
          "secondaryLine": [
            {
              "__typename": "MainSectionMessage",
              "body": "Jan 7 – 12",
              "bodyA11yLabel": null,
              "bodyType": null,
              "fontWeight": null,
              "headline": null,
              "type": "DATE"
            }
          ],
          "reviewSnippet": null,
          "explanation": []
        },
        "passportData": {},
        "paymentMessages": [],
        "kind": "",
        "name": "Michelin Guide Two Key stay in Napa",
        "title": "Hotel in Napa",
        "type": "",
        "long_stay_discount": {},
        "fee": {
          "airbnb": {},
          "cleaning": {}
        },
        "price": {
          "unit": {
            "qualifier": "for 5 nights",
            "curency_symbol": "$",
            "amount": 2279.0
          },
          "total": {
            "currency_symbol": "",
            "amount": 0
          },
          "break_down": [
            {
              "description": "5 nights x $455.76",
              "amount": 2278.0,
              "currency": "$.81"
            }
          ]
        },
        "rating": {
          "value": 0,
          "reviewCount": 0
        },
        "images": [
          {
            "url": "https://a0.muscache.com/im/pictures/prohost-api/Hosting-1172469018370689733/original/5180bc48-b91b-4800-aecb-74fd7a129450.jpeg"
          },
          {
            "url": "https://a0.muscache.com/im/pictures/prohost-api/Hosting-1172469018370689733/original/c21608a1-4c40-4cd8-a092-de46c7dad6f7.jpeg"
          },
          {
            "url": "https://a0.muscache.com/im/pictures/prohost-api/Hosting-1172469018370689733/original/35e3e5bd-e9d9-4ccf-b260-74fff2eb2361.jpeg"
          },
          {
            "url": "https://a0.muscache.com/im/pictures/prohost-api/Hosting-1172469018370689733/original/3ece29a7-bc1b-4a09-bc04-a50d3fc840e4.jpeg"
          },
          {
            "url": "https://a0.muscache.com/im/pictures/prohost-api/Hosting-1172469018370689733/original/469f50da-08f2-4d5c-872b-d04b55b77b76.jpeg"
          },
          {
            "url": "https://a0.muscache.com/im/pictures/prohost-api/Hosting-1172469018370689733/original/6c7b0af6-8bb6-4c78-8c12-63a4019548d7.jpeg"
          }
        ],
        "badges": [],
        "coordinates": {
          "latitude": 38.3151,
          "longitud": -122.2763
        }
      }
    }
  }
}