{
  "grid_id": 214,
  "total_listings": 5,
  "discovery_timestamp": "2025-12-26 10:02:04",
  "listings": {
    "1118682539263581146": {
      "room_id": 1118682539263581146,
      "latitude": 42.2034,
      "longitude": -83.5088,
      "grid_id_assigned": null,
      "grid_id_source": 214.0,
      "bbox_id": "42.189430_-83.528060_42.214870_-83.492510",
      "pass_id": 0,
      "discovered_at": "2025-12-26 09:59:10",
      "raw_data": {
        "room_id": 1118682539263581146,
        "category": "",
        "structuredContent": {
          "__typename": "ExploreStructuredContent",
          "distance": [],
          "mapCategoryInfo": [],
          "mapPrimaryLine": [],
          "mapSecondaryLine": [
            {
              "__typename": "MainSectionMessage",
              "body": "Jan 1 – 6",
              "bodyA11yLabel": null,
              "bodyType": null,
              "fontWeight": null,
              "headline": null,
              "type": "DATE"
            }
          ],
          "primaryLine": [
            {
              "__typename": "MainSectionMessage",
              "body": "4 bedrooms",
              "bodyA11yLabel": null,
              "bodyType": null,
              "fontWeight": null,
              "headline": null,
              "type": "BEDINFO"
            },
            {
              "__typename": "MainSectionMessage",
              "body": "4 beds",
              "bodyA11yLabel": null,
              "bodyType": null,
              "fontWeight": null,
              "headline": null,
              "type": "BEDINFO"
            }
          ],
          "secondaryLine": [
            {
              "__typename": "MainSectionMessage",
              "body": "Jan 1 – 6",
              "bodyA11yLabel": null,
              "bodyType": null,
              "fontWeight": null,
              "headline": null,
              "type": "DATE"
            }
          ],
          "reviewSnippet": null,
          "explanation": []
        },
        "passportData": {},
        "paymentMessages": [],
        "kind": "",
        "name": "Beautiful Comfy Lake Home",
        "title": "Home in Belleville",
        "type": "",
        "long_stay_discount": {},
        "fee": {
          "airbnb": {},
          "cleaning": {}
        },
        "price": {
          "unit": {
            "qualifier": "for 5 nights",
            "curency_symbol": "$",
            "amount": 1906.0
          },
          "total": {
            "currency_symbol": "",
            "amount": 0
          },
          "break_down": [
            {
              "description": "5 nights x $381.15",
              "amount": 1905.0,
              "currency": "$.77"
            }
          ]
        },
        "rating": {
          "value": 4.96,
          "reviewCount": "55"
        },
        "images": [
          {
            "url": "https://a0.muscache.com/im/pictures/hosting/Hosting-1118682539263581146/original/26a276d4-cf62-48bc-9f01-44f60ea3714c.jpeg"
          },
          {
            "url": "https://a0.muscache.com/im/pictures/hosting/Hosting-1118682539263581146/original/d8e3978c-2ddf-4f14-9e86-cd862f62907d.jpeg"
          },
          {
            "url": "https://a0.muscache.com/im/pictures/hosting/Hosting-1118682539263581146/original/ce730ff9-bf6c-494f-b9e3-e1585a4af29d.jpeg"
          },
          {
            "url": "https://a0.muscache.com/im/pictures/hosting/Hosting-1118682539263581146/original/9aa0b02f-88a8-4416-95b0-80e20355e7cf.jpeg"
          },
          {
            "url": "https://a0.muscache.com/im/pictures/hosting/Hosting-1118682539263581146/original/bcbfa036-393d-4303-a246-4149fec4f578.jpeg"
          },
          {
            "url": "https://a0.muscache.com/im/pictures/hosting/Hosting-1118682539263581146/original/f105b265-c1e6-4589-8293-dc77d7d683f8.jpeg"
          }
        ],
        "badges": [
          "TOP_X_GUEST_FAVORITE"
        ],
        "coordinates": {
          "latitude": 42.2034,
          "longitud": -83.5088
        }
      }
    },
    "1012677073913022748": {
      "room_id": 1012677073913022748,
      "latitude": 42.20202,
      "longitude": -83.49772,
      "grid_id_assigned": null,
      "grid_id_source": 214.0,
      "bbox_id": "42.189430_-83.528060_42.214870_-83.492510",
      "pass_id": 0,
      "discovered_at": "2025-12-26 09:59:10",
      "raw_data": {
        "room_id": 1012677073913022748,
        "category": "",
        "structuredContent": {
          "__typename": "ExploreStructuredContent",
          "distance": [],
          "mapCategoryInfo": [],
          "mapPrimaryLine": [],
          "mapSecondaryLine": [
            {
              "__typename": "MainSectionMessage",
              "body": "Jan 2 – 7",
              "bodyA11yLabel": null,
              "bodyType": null,
              "fontWeight": null,
              "headline": null,
              "type": "DATE"
            }
          ],
          "primaryLine": [
            {
              "__typename": "MainSectionMessage",
              "body": "3 bedrooms",
              "bodyA11yLabel": null,
              "bodyType": null,
              "fontWeight": null,
              "headline": null,
              "type": "BEDINFO"
            },
            {
              "__typename": "MainSectionMessage",
              "body": "4 beds",
              "bodyA11yLabel": null,
              "bodyType": null,
              "fontWeight": null,
              "headline": null,
              "type": "BEDINFO"
            }
          ],
          "secondaryLine": [
            {
              "__typename": "MainSectionMessage",
              "body": "Jan 2 – 7",
              "bodyA11yLabel": null,
              "bodyType": null,
              "fontWeight": null,
              "headline": null,
              "type": "DATE"
            }
          ],
          "reviewSnippet": null,
          "explanation": []
        },
        "passportData": {},
        "paymentMessages": [],
        "kind": "",
        "name": "Cozy Lakeside Home",
        "title": "Home in Belleville",
        "type": "",
        "long_stay_discount": {},
        "fee": {
          "airbnb": {},
          "cleaning": {}
        },
        "price": {
          "unit": {
            "qualifier": "for 5 nights",
            "curency_symbol": "$",
            "amount": 1735.0
          },
          "total": {
            "currency_symbol": "",
            "amount": 0
          },
          "break_down": [
            {
              "description": "5 nights x $346.92",
              "amount": 1734.0,
              "currency": "$.59"
            }
          ]
        },
        "rating": {
          "value": 4.89,
          "reviewCount": "38"
        },
        "images": [
          {
            "url": "https://a0.muscache.com/im/pictures/hosting/Hosting-1012677073913022748/original/b187f015-1df0-4696-88e6-f12608c6bda0.jpeg"
          },
          {
            "url": "https://a0.muscache.com/im/pictures/4bbd39de-70f1-432e-933e-b6b75cea96dd.jpg"
          },
          {
            "url": "https://a0.muscache.com/im/pictures/hosting/Hosting-1012677073913022748/original/29a951f2-abdf-4d6b-a8b5-aec38702635f.jpeg"
          },
          {
            "url": "https://a0.muscache.com/im/pictures/miso/Hosting-1012677073913022748/original/ff8a1562-a2cb-46ff-85ee-cb49a1d3601a.jpeg"
          },
          {
            "url": "https://a0.muscache.com/im/pictures/hosting/Hosting-1012677073913022748/original/09591692-ec7c-4c96-83c7-d22814d2043a.jpeg"
          },
          {
            "url": "https://a0.muscache.com/im/pictures/e29b78a4-e732-476f-971d-da05cbc656d7.jpg"
          }
        ],
        "badges": [
          "TOP_X_GUEST_FAVORITE"
        ],
        "coordinates": {
          "latitude": 42.20202,
          "longitud": -83.49772
        }
      }
    },
    "1399268911240847857": {
      "room_id": 1399268911240847857,
      "latitude": 42.2071,
      "longitude": -83.5144,
      "grid_id_assigned": null,
      "grid_id_source": 214.0,
      "bbox_id": "42.189430_-83.528060_42.214870_-83.492510",
      "pass_id": 0,
      "discovered_at": "2025-12-26 09:59:10",
      "raw_data": {
        "room_id": 1399268911240847857,
        "category": "",
        "structuredContent": {
          "__typename": "ExploreStructuredContent",
          "distance": [],
          "mapCategoryInfo": [],
          "mapPrimaryLine": [],
          "mapSecondaryLine": [
            {
              "__typename": "MainSectionMessage",
              "body": "Jan 2 – 7",
              "bodyA11yLabel": null,
              "bodyType": null,
              "fontWeight": null,
              "headline": null,
              "type": "DATE"
            }
          ],
          "primaryLine": [
            {
              "__typename": "MainSectionMessage",
              "body": "3 bedrooms",
              "bodyA11yLabel": null,
              "bodyType": null,
              "fontWeight": null,
              "headline": null,
              "type": "BEDINFO"
            },
            {
              "__typename": "MainSectionMessage",
              "body": "5 beds",
              "bodyA11yLabel": null,
              "bodyType": null,
              "fontWeight": null,
              "headline": null,
              "type": "BEDINFO"
            }
          ],
          "secondaryLine": [
            {
              "__typename": "MainSectionMessage",
              "body": "Jan 2 – 7",
              "bodyA11yLabel": null,
              "bodyType": null,
              "fontWeight": null,
              "headline": null,
              "type": "DATE"
            }
          ],
          "reviewSnippet": null,
          "explanation": []
        },
        "passportData": {},
        "paymentMessages": [],
        "kind": "",
        "name": "Ice Fishing & Winter Hikes! Belleville Lake House",
        "title": "Home in Belleville",
        "type": "",
        "long_stay_discount": {},
        "fee": {
          "airbnb": {},
          "cleaning": {}
        },
        "price": {
          "unit": {
            "qualifier": "for 5 nights",
            "curency_symbol": "$",
            "amount": 1225.0
          },
          "total": {
            "currency_symbol": "",
            "amount": 0
          },
          "break_down": [
            {
              "description": "5 nights x $245.00",
              "amount": 1225.0,
              "currency": "$.00"
            }
          ]
        },
        "rating": {
          "value": 4.17,
          "reviewCount": "12"
        },
        "images": [
          {
            "url": "https://a0.muscache.com/im/pictures/prohost-api/Hosting-1399268911240847857/original/35b161bf-331b-42c7-99ab-06570094c0b8.jpeg"
          },
          {
            "url": "https://a0.muscache.com/im/pictures/prohost-api/Hosting-1399268911240847857/original/2637acb4-b0c6-44e1-96d3-86c2a3f30148.jpeg"
          },
          {
            "url": "https://a0.muscache.com/im/pictures/prohost-api/Hosting-1399268911240847857/original/baa4edf7-9fa7-4a52-aa4c-2aa41275ad4f.jpeg"
          },
          {
            "url": "https://a0.muscache.com/im/pictures/prohost-api/Hosting-1399268911240847857/original/b5057025-2aed-494d-8fb2-591fcae2de1c.jpeg"
          },
          {
            "url": "https://a0.muscache.com/im/pictures/prohost-api/Hosting-1399268911240847857/original/fd54ffc8-887a-477a-8156-671dfe81d1a3.jpeg"
          },
          {
            "url": "https://a0.muscache.com/im/pictures/prohost-api/Hosting-1399268911240847857/original/b32c7601-e96f-41be-80f1-7361e22472a9.jpeg"
          }
        ],
        "badges": [],
        "coordinates": {
          "latitude": 42.2071,
          "longitud": -83.5144
        }
      }
    },
    "976097519487322839": {
      "room_id": 976097519487322839,
      "latitude": 42.18956,
      "longitude": -83.50383,
      "grid_id_assigned": null,
      "grid_id_source": 214.0,
      "bbox_id": "42.189430_-83.528060_42.214870_-83.492510",
      "pass_id": 0,
      "discovered_at": "2025-12-26 09:59:10",
      "raw_data": {
        "room_id": 976097519487322839,
        "category": "",
        "structuredContent": {
          "__typename": "ExploreStructuredContent",
          "distance": [],
          "mapCategoryInfo": [],
          "mapPrimaryLine": [],
          "mapSecondaryLine": [
            {
              "__typename": "MainSectionMessage",
              "body": "Jan 1 – 6",
              "bodyA11yLabel": null,
              "bodyType": null,
              "fontWeight": null,
              "headline": null,
              "type": "DATE"
            }
          ],
          "primaryLine": [
            {
              "__typename": "MainSectionMessage",
              "body": "2 bedrooms",
              "bodyA11yLabel": null,
              "bodyType": null,
              "fontWeight": null,
              "headline": null,
              "type": "BEDINFO"
            },
            {
              "__typename": "MainSectionMessage",
              "body": "4 beds",
              "bodyA11yLabel": null,
              "bodyType": null,
              "fontWeight": null,
              "headline": null,
              "type": "BEDINFO"
            }
          ],
          "secondaryLine": [
            {
              "__typename": "MainSectionMessage",
              "body": "Jan 1 – 6",
              "bodyA11yLabel": null,
              "bodyType": null,
              "fontWeight": null,
              "headline": null,
              "type": "DATE"
            }
          ],
          "reviewSnippet": null,
          "explanation": []
        },
        "passportData": {},
        "paymentMessages": [],
        "kind": "",
        "name": "The Roaming Sunny Beach House",
        "title": "Camper/RV in Belleville",
        "type": "",
        "long_stay_discount": {},
        "fee": {
          "airbnb": {},
          "cleaning": {}
        },
        "price": {
          "unit": {
            "qualifier": "for 5 nights",
            "curency_symbol": "$",
            "amount": 1225.0,
            "discount": 1005.0
          },
          "total": {
            "currency_symbol": "",
            "amount": 0
          },
          "break_down": [
            {
              "description": "5 nights x $244.85",
              "amount": 1224.0,
              "currency": "$.24"
            },
            {
              "description": "Special offer",
              "amount": -220.0,
              "currency": "$.00"
            },
            {
              "description": "Price after discount",
              "amount": 1004.0,
              "currency": "$.24"
            }
          ]
        },
        "rating": {
          "value": 0,
          "reviewCount": 0
        },
        "images": [
          {
            "url": "https://a0.muscache.com/im/pictures/miso/Hosting-976097519487322839/original/9011782d-bb36-4110-ae12-df916f0f0ce0.jpeg"
          },
          {
            "url": "https://a0.muscache.com/im/pictures/miso/Hosting-976097519487322839/original/9d5533a0-ceb1-46f2-91cd-12482bec4d05.jpeg"
          },
          {
            "url": "https://a0.muscache.com/im/pictures/miso/Hosting-976097519487322839/original/7f4e44e2-624f-485a-a809-4ae452398d02.jpeg"
          },
          {
            "url": "https://a0.muscache.com/im/pictures/miso/Hosting-976097519487322839/original/f6d84f89-1204-48b3-8c50-bdf31b29601a.jpeg"
          },
          {
            "url": "https://a0.muscache.com/im/pictures/miso/Hosting-976097519487322839/original/5b2decd3-99d3-4df5-9174-a9a5bfb40f15.jpeg"
          },
          {
            "url": "https://a0.muscache.com/im/pictures/miso/Hosting-976097519487322839/original/8cec0837-8152-4c0f-b7bf-54775518d623.jpeg"
          }
        ],
        "badges": [],
        "coordinates": {
          "latitude": 42.18956,
          "longitud": -83.50383
        }
      }
    },
    "1132788487980462098": {
      "room_id": 1132788487980462098,
      "latitude": 42.2055,
      "longitude": -83.5199,
      "grid_id_assigned": null,
      "grid_id_source": 214.0,
      "bbox_id": "42.189430_-83.528060_42.214870_-83.492510",
      "pass_id": 0,
      "discovered_at": "2025-12-26 09:59:10",
      "raw_data": {
        "room_id": 1132788487980462098,
        "category": "",
        "structuredContent": {
          "__typename": "ExploreStructuredContent",
          "distance": [],
          "mapCategoryInfo": [],
          "mapPrimaryLine": [],
          "mapSecondaryLine": [
            {
              "__typename": "MainSectionMessage",
              "body": "Jan 1 – 6",
              "bodyA11yLabel": null,
              "bodyType": null,
              "fontWeight": null,
              "headline": null,
              "type": "DATE"
            }
          ],
          "primaryLine": [
            {
              "__typename": "MainSectionMessage",
              "body": "4 bedrooms",
              "bodyA11yLabel": null,
              "bodyType": null,
              "fontWeight": null,
              "headline": null,
              "type": "BEDINFO"
            },
            {
              "__typename": "MainSectionMessage",
              "body": "4 beds",
              "bodyA11yLabel": null,
              "bodyType": null,
              "fontWeight": null,
              "headline": null,
              "type": "BEDINFO"
            }
          ],
          "secondaryLine": [
            {
              "__typename": "MainSectionMessage",
              "body": "Jan 1 – 6",
              "bodyA11yLabel": null,
              "bodyType": null,
              "fontWeight": null,
              "headline": null,
              "type": "DATE"
            }
          ],
          "reviewSnippet": null,
          "explanation": []
        },
        "passportData": {},
        "paymentMessages": [],
        "kind": "",
        "name": "NourishingNest min from Downtown Detroit/Ann Arbor",
        "title": "Home in Van Buren Charter Township",
        "type": "",
        "long_stay_discount": {},
        "fee": {
          "airbnb": {},
          "cleaning": {}
        },
        "price": {
          "unit": {
            "qualifier": "for 5 nights",
            "curency_symbol": "$",
            "amount": 2528.0
          },
          "total": {
            "currency_symbol": "",
            "amount": 0
          },
          "break_down": [
            {
              "description": "5 nights x $505.54",
              "amount": 2527.0,
              "currency": "$.71"
            }
          ]
        },
        "rating": {
          "value": 0,
          "reviewCount": 0
        },
        "images": [
          {
            "url": "https://a0.muscache.com/im/pictures/hosting/Hosting-1132788487980462098/original/d63ba298-fd6d-4827-8f04-2991a932678f.jpeg"
          },
          {
            "url": "https://a0.muscache.com/im/pictures/hosting/Hosting-1132788487980462098/original/36459028-839c-4d5b-bc58-3c0d8c299b6a.jpeg"
          },
          {
            "url": "https://a0.muscache.com/im/pictures/hosting/Hosting-1132788487980462098/original/a99881f6-1d9f-4d24-8750-6a561aae16cb.jpeg"
          },
          {
            "url": "https://a0.muscache.com/im/pictures/hosting/Hosting-1132788487980462098/original/9d737500-5162-4522-9ea8-241a46f31a90.jpeg"
          },
          {
            "url": "https://a0.muscache.com/im/pictures/hosting/Hosting-1132788487980462098/original/599a44b8-f3fd-41ed-abe2-b844fae902d7.jpeg"
          },
          {
            "url": "https://a0.muscache.com/im/pictures/hosting/Hosting-1132788487980462098/original/98e5a38f-3f9e-4bcc-9054-9e3a4bcc954a.jpeg"
          }
        ],
        "badges": [],
        "coordinates": {
          "latitude": 42.2055,
          "longitud": -83.5199
        }
      }
    }
  }
}